setup.cfg
setup.py
Dittopy.egg-info/PKG-INFO
Dittopy.egg-info/SOURCES.txt
Dittopy.egg-info/dependency_links.txt
Dittopy.egg-info/top_level.txt
ditto/__init__.py
ditto/ditto.py