Metadata-Version: 1.0
Name: Dittopy
Version: 0.0.1
Summary: Lazy config variable handler.
Home-page: https://github.com/lahlali/Ditto.py
Author: Anass LAHLALI
Author-email: anass.lahlali@hotmail.com
License: UNKNOWN
Keywords: lazy,config,variable,handler
Platform: UNKNOWN
